Steam_Tracker/__init__.py
Steam_Tracker/steam_tracker.py
SteamTracker-0.0.1.dist-info/METADATA
SteamTracker-0.0.1.dist-info/WHEEL
SteamTracker-0.0.1.dist-info/top_level.txt
SteamTracker-0.0.1.dist-info/RECORD
