Metadata-Version: 2.1
Name: SteamTracker
Version: 0.0.1
Summary: Checks Steam Game Pricing
Author: Follen
Author-email: <binor15175@brandoza.com>
Keywords: python,video,stream,video stream,camera stream,sockets
Classifier: Development Status :: 5 - Production/Stable
Classifier: Intended Audience :: Developers
Classifier: Programming Language :: Python :: 3
Classifier: Operating System :: Unix
Classifier: Operating System :: MacOS :: MacOS X
Classifier: Operating System :: Microsoft :: Windows
Requires-Dist: requests
Requires-Dist: bs4
Requires-Dist: time
